{
    "version": "https://jsonfeed.org/version/1",
    "title": "NORWAY 2023",
    "description": "",
    "home_page_url": "https://frau-urlaub-on-tour.github.io/norway-2023",
    "feed_url": "https://frau-urlaub-on-tour.github.io/norway-2023/feed.json",
    "user_comment": "",
    "author": {
        "name": "Petra"
    },
    "items": [
        {
            "id": "https://frau-urlaub-on-tour.github.io/norway-2023/day-1-on-the-road.html",
            "url": "https://frau-urlaub-on-tour.github.io/norway-2023/day-1-on-the-road.html",
            "title": "Day 1 on the road",
            "summary": "A brilliant first driving day. The weather isn't as bad&hellip;",
            "content_html": "<p>A brilliant first driving day. The weather isn't as bad as I feared after waking up to pouring rain. The atmosphere changes quickly from bright and sunny to dark and moody. Great for taking pictures. The going is quite slow with speed limits often at 60 km, never more than 80 km. Fortunately, the main tourist season is over and there are only very few cars on the roads, and most of them are travelling South and not like me up North. The most interesting part of the trip are the frequent tunnels, sometimes up to 5 km long. Nothing for the claustrophobic ones, they tend to be rather narrow and dark. I reach my first destination Grotli after about 360 km and a total driving time of about 6 hours. Winding down in the cozy Hotel bar with a nice Norwegian Gin &amp; Tonic.</p>\n<div class=\"gallery-wrapper\"><div class=\"gallery\"  data-is-empty=\"false\" data-translation=\"Add images\" data-columns=\"3\">\n<figure class=\"gallery__item\"><a href=\"https://frau-urlaub-on-tour.github.io/norway-2023/media/posts/32/gallery/IMG_3804.JPG\" data-size=\"1920x1080\"><img loading=\"lazy\" src=\"https://frau-urlaub-on-tour.github.io/norway-2023/media/posts/32/gallery/IMG_3804-thumbnail.JPG\" alt=\"\" width=\"720\" height=\"405\"></a></figure>\n<figure class=\"gallery__item\"><a href=\"https://frau-urlaub-on-tour.github.io/norway-2023/media/posts/32/gallery/IMG_3806.JPG\" data-size=\"1920x1080\"><img loading=\"lazy\" src=\"https://frau-urlaub-on-tour.github.io/norway-2023/media/posts/32/gallery/IMG_3806-thumbnail.JPG\" alt=\"\" width=\"720\" height=\"405\"></a></figure>\n<figure class=\"gallery__item\"><a href=\"https://frau-urlaub-on-tour.github.io/norway-2023/media/posts/32/gallery/IMG_3807.JPG\" data-size=\"1920x1080\"><img loading=\"lazy\" src=\"https://frau-urlaub-on-tour.github.io/norway-2023/media/posts/32/gallery/IMG_3807-thumbnail.JPG\" alt=\"\" width=\"720\" height=\"405\"></a></figure>\n<figure class=\"gallery__item\"><a href=\"https://frau-urlaub-on-tour.github.io/norway-2023/media/posts/32/gallery/IMG_3808.JPG\" data-size=\"1920x1080\"><img loading=\"lazy\" src=\"https://frau-urlaub-on-tour.github.io/norway-2023/media/posts/32/gallery/IMG_3808-thumbnail.JPG\" alt=\"\" width=\"720\" height=\"405\"></a></figure>\n<figure class=\"gallery__item\"><a href=\"https://frau-urlaub-on-tour.github.io/norway-2023/media/posts/32/gallery/IMG_20230822_143937318.jpg\" data-size=\"1920x1080\"><img loading=\"lazy\" src=\"https://frau-urlaub-on-tour.github.io/norway-2023/media/posts/32/gallery/IMG_20230822_143937318-thumbnail.jpg\" alt=\"\" width=\"720\" height=\"405\"></a></figure>\n<figure class=\"gallery__item\"><a href=\"https://frau-urlaub-on-tour.github.io/norway-2023/media/posts/32/gallery/IMG_3809.JPG\" data-size=\"1920x1080\"><img loading=\"lazy\" src=\"https://frau-urlaub-on-tour.github.io/norway-2023/media/posts/32/gallery/IMG_3809-thumbnail.JPG\" alt=\"\" width=\"720\" height=\"405\"></a></figure>\n<figure class=\"gallery__item\"><a href=\"https://frau-urlaub-on-tour.github.io/norway-2023/media/posts/32/gallery/IMG_3810.JPG\" data-size=\"1920x1080\"><img loading=\"lazy\" src=\"https://frau-urlaub-on-tour.github.io/norway-2023/media/posts/32/gallery/IMG_3810-thumbnail.JPG\" alt=\"\" width=\"720\" height=\"405\"></a></figure>\n<figure class=\"gallery__item\"><a href=\"https://frau-urlaub-on-tour.github.io/norway-2023/media/posts/32/gallery/IMG_3812.JPG\" data-size=\"1920x1080\"><img loading=\"lazy\" src=\"https://frau-urlaub-on-tour.github.io/norway-2023/media/posts/32/gallery/IMG_3812-thumbnail.JPG\" alt=\"\" width=\"720\" height=\"405\"></a></figure>\n<figure class=\"gallery__item\"><a href=\"https://frau-urlaub-on-tour.github.io/norway-2023/media/posts/32/gallery/IMG_3813.JPG\" data-size=\"1920x1080\"><img loading=\"lazy\" src=\"https://frau-urlaub-on-tour.github.io/norway-2023/media/posts/32/gallery/IMG_3813-thumbnail.JPG\" alt=\"\" width=\"720\" height=\"405\"></a></figure>\n<figure class=\"gallery__item\"><a href=\"https://frau-urlaub-on-tour.github.io/norway-2023/media/posts/32/gallery/IMG_3814.JPG\" data-size=\"1920x1080\"><img loading=\"lazy\" src=\"https://frau-urlaub-on-tour.github.io/norway-2023/media/posts/32/gallery/IMG_3814-thumbnail.JPG\" alt=\"\" width=\"720\" height=\"405\"></a></figure>\n<figure class=\"gallery__item\"><a href=\"https://frau-urlaub-on-tour.github.io/norway-2023/media/posts/32/gallery/IMG_3816.JPG\" data-size=\"1920x1080\"><img loading=\"lazy\" src=\"https://frau-urlaub-on-tour.github.io/norway-2023/media/posts/32/gallery/IMG_3816-thumbnail.JPG\" alt=\"\" width=\"720\" height=\"405\"></a></figure>\n<figure class=\"gallery__item\"><a href=\"https://frau-urlaub-on-tour.github.io/norway-2023/media/posts/32/gallery/IMG_3817.JPG\" data-size=\"1920x1080\"><img loading=\"lazy\" src=\"https://frau-urlaub-on-tour.github.io/norway-2023/media/posts/32/gallery/IMG_3817-thumbnail.JPG\" alt=\"\" width=\"720\" height=\"405\"></a></figure>\n<figure class=\"gallery__item\"><a href=\"https://frau-urlaub-on-tour.github.io/norway-2023/media/posts/32/gallery/IMG_3818.JPG\" data-size=\"1920x1080\"><img loading=\"lazy\" src=\"https://frau-urlaub-on-tour.github.io/norway-2023/media/posts/32/gallery/IMG_3818-thumbnail.JPG\" alt=\"\" width=\"720\" height=\"405\"></a></figure>\n<figure class=\"gallery__item\"><a href=\"https://frau-urlaub-on-tour.github.io/norway-2023/media/posts/32/gallery/IMG_3819.JPG\" data-size=\"1920x1080\"><img loading=\"lazy\" src=\"https://frau-urlaub-on-tour.github.io/norway-2023/media/posts/32/gallery/IMG_3819-thumbnail.JPG\" alt=\"\" width=\"720\" height=\"405\"></a></figure>\n<figure class=\"gallery__item\"><a href=\"https://frau-urlaub-on-tour.github.io/norway-2023/media/posts/32/gallery/IMG_3820.JPG\" data-size=\"1920x1080\"><img loading=\"lazy\" src=\"https://frau-urlaub-on-tour.github.io/norway-2023/media/posts/32/gallery/IMG_3820-thumbnail.JPG\" alt=\"\" width=\"720\" height=\"405\"></a></figure>\n<figure class=\"gallery__item\"><a href=\"https://frau-urlaub-on-tour.github.io/norway-2023/media/posts/32/gallery/IMG_3821.JPG\" data-size=\"1920x1080\"><img loading=\"lazy\" src=\"https://frau-urlaub-on-tour.github.io/norway-2023/media/posts/32/gallery/IMG_3821-thumbnail.JPG\" alt=\"\" width=\"720\" height=\"405\"></a></figure>\n<figure class=\"gallery__item\"><a href=\"https://frau-urlaub-on-tour.github.io/norway-2023/media/posts/32/gallery/IMG_3822.JPG\" data-size=\"1920x1080\"><img loading=\"lazy\" src=\"https://frau-urlaub-on-tour.github.io/norway-2023/media/posts/32/gallery/IMG_3822-thumbnail.JPG\" alt=\"\" width=\"720\" height=\"405\"></a></figure>\n<figure class=\"gallery__item\"><a href=\"https://frau-urlaub-on-tour.github.io/norway-2023/media/posts/32/gallery/IMG_3823.JPG\" data-size=\"1920x1080\"><img loading=\"lazy\" src=\"https://frau-urlaub-on-tour.github.io/norway-2023/media/posts/32/gallery/IMG_3823-thumbnail.JPG\" alt=\"\" width=\"720\" height=\"405\"></a></figure>\n<figure class=\"gallery__item\"><a href=\"https://frau-urlaub-on-tour.github.io/norway-2023/media/posts/32/gallery/IMG_20230822_181213884.jpg\" data-size=\"1920x1080\"><img loading=\"lazy\" src=\"https://frau-urlaub-on-tour.github.io/norway-2023/media/posts/32/gallery/IMG_20230822_181213884-thumbnail.jpg\" alt=\"\" width=\"720\" height=\"405\"></a></figure>\n<figure class=\"gallery__item\"><a href=\"https://frau-urlaub-on-tour.github.io/norway-2023/media/posts/32/gallery/IMG_3824.JPG\" data-size=\"1920x1080\"><img loading=\"lazy\" src=\"https://frau-urlaub-on-tour.github.io/norway-2023/media/posts/32/gallery/IMG_3824-thumbnail.JPG\" alt=\"\" width=\"720\" height=\"405\"></a></figure>\n<figure class=\"gallery__item\"><a href=\"https://frau-urlaub-on-tour.github.io/norway-2023/media/posts/32/gallery/IMG_3828.JPG\" data-size=\"1920x1080\"><img loading=\"lazy\" src=\"https://frau-urlaub-on-tour.github.io/norway-2023/media/posts/32/gallery/IMG_3828-thumbnail.JPG\" alt=\"\" width=\"720\" height=\"405\"></a></figure>\n<figure class=\"gallery__item\"><a href=\"https://frau-urlaub-on-tour.github.io/norway-2023/media/posts/32/gallery/IMG_3829.JPG\" data-size=\"1920x1080\"><img loading=\"lazy\" src=\"https://frau-urlaub-on-tour.github.io/norway-2023/media/posts/32/gallery/IMG_3829-thumbnail.JPG\" alt=\"\" width=\"720\" height=\"405\"></a></figure>\n<figure class=\"gallery__item\"><a href=\"https://frau-urlaub-on-tour.github.io/norway-2023/media/posts/32/gallery/IMG_3830.JPG\" data-size=\"1920x1080\"><img loading=\"lazy\" src=\"https://frau-urlaub-on-tour.github.io/norway-2023/media/posts/32/gallery/IMG_3830-thumbnail.JPG\" alt=\"\" width=\"720\" height=\"405\"></a></figure>\n<figure class=\"gallery__item\"><a href=\"https://frau-urlaub-on-tour.github.io/norway-2023/media/posts/32/gallery/WhatsApp-Bild-2023-08-22-um-22.42.45.jpg\" data-size=\"1920x1080\"><img loading=\"lazy\" src=\"https://frau-urlaub-on-tour.github.io/norway-2023/media/posts/32/gallery/WhatsApp-Bild-2023-08-22-um-22.42.45-thumbnail.jpg\" alt=\"\" width=\"720\" height=\"405\"></a></figure>\n</div></div>",
            "image": "https://frau-urlaub-on-tour.github.io/norway-2023/media/posts/32/IMG_3826.JPG",
            "author": {
                "name": "Petra"
            },
            "tags": [
            ],
            "date_published": "2023-08-22T21:04:00+02:00",
            "date_modified": "2023-08-22T22:48:21+02:00"
        },
        {
            "id": "https://frau-urlaub-on-tour.github.io/norway-2023/through-the-water-maze.html",
            "url": "https://frau-urlaub-on-tour.github.io/norway-2023/through-the-water-maze.html",
            "title": "Through the Water Maze",
            "summary": "The last stretch from Stavangar to Bergen is quite dramatic&hellip;",
            "content_html": "<p>The last stretch from Stavangar to Bergen is quite dramatic as the ferry takes a route through what I would describe as a \"Water Maze\" passing by little islands and stretches of coastline that are connected by yet more ferries. A truly amazing scenery. Even more so as it has stopped raining cats and dogs and changed into a mixture of clouds and sunny spells.</p>\n<div class=\"gallery-wrapper\"><div class=\"gallery\"  data-is-empty=\"false\" data-translation=\"Add images\" data-columns=\"3\">\n<figure class=\"gallery__item\"><a href=\"https://frau-urlaub-on-tour.github.io/norway-2023/media/posts/31/gallery/IMG_3779-2.JPG\" data-size=\"1920x1080\"><img loading=\"lazy\" src=\"https://frau-urlaub-on-tour.github.io/norway-2023/media/posts/31/gallery/IMG_3779-2-thumbnail.JPG\" alt=\"\" width=\"720\" height=\"405\"></a></figure>\n<figure class=\"gallery__item\"><a href=\"https://frau-urlaub-on-tour.github.io/norway-2023/media/posts/31/gallery/IMG_3780-2.JPG\" data-size=\"1920x1080\"><img loading=\"lazy\" src=\"https://frau-urlaub-on-tour.github.io/norway-2023/media/posts/31/gallery/IMG_3780-2-thumbnail.JPG\" alt=\"\" width=\"720\" height=\"405\"></a></figure>\n<figure class=\"gallery__item\"><a href=\"https://frau-urlaub-on-tour.github.io/norway-2023/media/posts/31/gallery/IMG_3781-2.JPG\" data-size=\"1920x1080\"><img loading=\"lazy\" src=\"https://frau-urlaub-on-tour.github.io/norway-2023/media/posts/31/gallery/IMG_3781-2-thumbnail.JPG\" alt=\"\" width=\"720\" height=\"405\"></a></figure>\n<figure class=\"gallery__item\"><a href=\"https://frau-urlaub-on-tour.github.io/norway-2023/media/posts/31/gallery/IMG_3782-2.JPG\" data-size=\"1920x1080\"><img loading=\"lazy\" src=\"https://frau-urlaub-on-tour.github.io/norway-2023/media/posts/31/gallery/IMG_3782-2-thumbnail.JPG\" alt=\"\" width=\"720\" height=\"405\"></a></figure>\n<figure class=\"gallery__item\"><a href=\"https://frau-urlaub-on-tour.github.io/norway-2023/media/posts/31/gallery/IMG_3783-2.JPG\" data-size=\"1920x1080\"><img loading=\"lazy\" src=\"https://frau-urlaub-on-tour.github.io/norway-2023/media/posts/31/gallery/IMG_3783-2-thumbnail.JPG\" alt=\"\" width=\"720\" height=\"405\"></a></figure>\n<figure class=\"gallery__item\"><a href=\"https://frau-urlaub-on-tour.github.io/norway-2023/media/posts/31/gallery/IMG_3784-2.JPG\" data-size=\"1920x1080\"><img loading=\"lazy\" src=\"https://frau-urlaub-on-tour.github.io/norway-2023/media/posts/31/gallery/IMG_3784-2-thumbnail.JPG\" alt=\"\" width=\"720\" height=\"405\"></a></figure>\n<figure class=\"gallery__item\"><a href=\"https://frau-urlaub-on-tour.github.io/norway-2023/media/posts/31/gallery/IMG_3785-2.JPG\" data-size=\"1920x1080\"><img loading=\"lazy\" src=\"https://frau-urlaub-on-tour.github.io/norway-2023/media/posts/31/gallery/IMG_3785-2-thumbnail.JPG\" alt=\"\" width=\"720\" height=\"405\"></a></figure>\n<figure class=\"gallery__item\"><a href=\"https://frau-urlaub-on-tour.github.io/norway-2023/media/posts/31/gallery/IMG_3787-2.JPG\" data-size=\"1920x1080\"><img loading=\"lazy\" src=\"https://frau-urlaub-on-tour.github.io/norway-2023/media/posts/31/gallery/IMG_3787-2-thumbnail.JPG\" alt=\"\" width=\"720\" height=\"405\"></a></figure>\n<figure class=\"gallery__item\"><a href=\"https://frau-urlaub-on-tour.github.io/norway-2023/media/posts/31/gallery/IMG_3789-2.JPG\" data-size=\"1920x1080\"><img loading=\"lazy\" src=\"https://frau-urlaub-on-tour.github.io/norway-2023/media/posts/31/gallery/IMG_3789-2-thumbnail.JPG\" alt=\"\" width=\"720\" height=\"405\"></a></figure>\n<figure class=\"gallery__item\"><a href=\"https://frau-urlaub-on-tour.github.io/norway-2023/media/posts/31/gallery/IMG_3790.JPG\" data-size=\"1920x1080\"><img loading=\"lazy\" src=\"https://frau-urlaub-on-tour.github.io/norway-2023/media/posts/31/gallery/IMG_3790-thumbnail.JPG\" alt=\"\" width=\"720\" height=\"405\"></a></figure>\n<figure class=\"gallery__item\"><a href=\"https://frau-urlaub-on-tour.github.io/norway-2023/media/posts/31/gallery/IMG_3791-2.JPG\" data-size=\"1920x1080\"><img loading=\"lazy\" src=\"https://frau-urlaub-on-tour.github.io/norway-2023/media/posts/31/gallery/IMG_3791-2-thumbnail.JPG\" alt=\"\" width=\"720\" height=\"405\"></a></figure>\n<figure class=\"gallery__item\"><a href=\"https://frau-urlaub-on-tour.github.io/norway-2023/media/posts/31/gallery/IMG_3792-2.JPG\" data-size=\"1920x1080\"><img loading=\"lazy\" src=\"https://frau-urlaub-on-tour.github.io/norway-2023/media/posts/31/gallery/IMG_3792-2-thumbnail.JPG\" alt=\"\" width=\"720\" height=\"405\"></a></figure>\n<figure class=\"gallery__item\"><a href=\"https://frau-urlaub-on-tour.github.io/norway-2023/media/posts/31/gallery/IMG_3794-2.JPG\" data-size=\"1920x1080\"><img loading=\"lazy\" src=\"https://frau-urlaub-on-tour.github.io/norway-2023/media/posts/31/gallery/IMG_3794-2-thumbnail.JPG\" alt=\"\" width=\"720\" height=\"405\"></a></figure>\n<figure class=\"gallery__item\"><a href=\"https://frau-urlaub-on-tour.github.io/norway-2023/media/posts/31/gallery/IMG_3795-2.JPG\" data-size=\"1920x1080\"><img loading=\"lazy\" src=\"https://frau-urlaub-on-tour.github.io/norway-2023/media/posts/31/gallery/IMG_3795-2-thumbnail.JPG\" alt=\"\" width=\"720\" height=\"405\"></a></figure>\n<figure class=\"gallery__item\"><a href=\"https://frau-urlaub-on-tour.github.io/norway-2023/media/posts/31/gallery/IMG_3800-2.JPG\" data-size=\"1920x1080\"><img loading=\"lazy\" src=\"https://frau-urlaub-on-tour.github.io/norway-2023/media/posts/31/gallery/IMG_3800-2-thumbnail.JPG\" alt=\"\" width=\"720\" height=\"405\"></a></figure>\n<figure class=\"gallery__item\"><a href=\"https://frau-urlaub-on-tour.github.io/norway-2023/media/posts/31/gallery/IMG_3801-2.JPG\" data-size=\"1920x1080\"><img loading=\"lazy\" src=\"https://frau-urlaub-on-tour.github.io/norway-2023/media/posts/31/gallery/IMG_3801-2-thumbnail.JPG\" alt=\"\" width=\"720\" height=\"405\"></a></figure>\n<figure class=\"gallery__item\"><a href=\"https://frau-urlaub-on-tour.github.io/norway-2023/media/posts/31/gallery/IMG_3802-2.JPG\" data-size=\"1920x1080\"><img loading=\"lazy\" src=\"https://frau-urlaub-on-tour.github.io/norway-2023/media/posts/31/gallery/IMG_3802-2-thumbnail.JPG\" alt=\"\" width=\"720\" height=\"405\"></a></figure>\n<figure class=\"gallery__item\"><a href=\"https://frau-urlaub-on-tour.github.io/norway-2023/media/posts/31/gallery/IMG_3803-2.JPG\" data-size=\"1920x1080\"><img loading=\"lazy\" src=\"https://frau-urlaub-on-tour.github.io/norway-2023/media/posts/31/gallery/IMG_3803-2-thumbnail.JPG\" alt=\"\" width=\"720\" height=\"405\"></a></figure>\n</div></div>\n<p class=\"align-center\">Click on the gallery then swipe or use ← → keys</p>\n<div class=\"gallery-wrapper\"><div class=\"gallery\"  data-is-empty=\"false\" data-translation=\"Add images\" data-columns=\"3\"> </div></div>",
            "image": "https://frau-urlaub-on-tour.github.io/norway-2023/media/posts/31/IMG_3796.JPG",
            "author": {
                "name": "Petra"
            },
            "tags": [
            ],
            "date_published": "2023-08-22T12:01:00+02:00",
            "date_modified": "2023-08-22T22:03:49+02:00"
        },
        {
            "id": "https://frau-urlaub-on-tour.github.io/norway-2023/the-crossing-2.html",
            "url": "https://frau-urlaub-on-tour.github.io/norway-2023/the-crossing-2.html",
            "title": "The Crossing",
            "summary": "Ferry leaves before departure time. That must be Scandinavian efficiency.",
            "content_html": "<p>Ferry leaves before departure time. That must be Scandinavian efficiency. My cabin is cozy, the bed comfy and the crossing surprisingly calm and not rocky. Waking up at 6 am when we reach our first stop Stavangar. It's still dark outside but I can sense the rain. Which proves to be true when I next wake up two hours later. Good morning Norway. And a big smiley hello to wet weather.</p>\n<div class=\"gallery-wrapper\"><div class=\"gallery\"  data-is-empty=\"false\" data-translation=\"Add images\" data-columns=\"3\">\n<figure class=\"gallery__item\"><a href=\"https://frau-urlaub-on-tour.github.io/norway-2023/media/posts/30/gallery/IMG_20230821_191808117.jpg\" data-size=\"4080x2296\"><img loading=\"lazy\" src=\"https://frau-urlaub-on-tour.github.io/norway-2023/media/posts/30/gallery/IMG_20230821_191808117-thumbnail.jpg\" alt=\"\" width=\"720\" height=\"405\"></a></figure>\n<figure class=\"gallery__item\"><a href=\"https://frau-urlaub-on-tour.github.io/norway-2023/media/posts/30/gallery/IMG_20230821_193313143.jpg\" data-size=\"3264x1836\"><img loading=\"lazy\" src=\"https://frau-urlaub-on-tour.github.io/norway-2023/media/posts/30/gallery/IMG_20230821_193313143-thumbnail.jpg\" alt=\"\" width=\"720\" height=\"405\"></a></figure>\n<figure class=\"gallery__item\"><a href=\"https://frau-urlaub-on-tour.github.io/norway-2023/media/posts/30/gallery/WhatsApp-Bild-2023-08-22-um-08.19.49.jpg\" data-size=\"1600x900\"><img loading=\"lazy\" src=\"https://frau-urlaub-on-tour.github.io/norway-2023/media/posts/30/gallery/WhatsApp-Bild-2023-08-22-um-08.19.49-thumbnail.jpg\" alt=\"\" width=\"720\" height=\"405\"></a></figure>\n</div></div>\n<p class=\"align-center\">Click on the gallery then swipe or use ← → keys</p>",
            "image": "https://frau-urlaub-on-tour.github.io/norway-2023/media/posts/30/IMG_20230821_191409188.jpg",
            "author": {
                "name": "Petra"
            },
            "tags": [
            ],
            "date_published": "2023-08-22T08:36:00+02:00",
            "date_modified": "2023-08-22T22:02:13+02:00"
        },
        {
            "id": "https://frau-urlaub-on-tour.github.io/norway-2023/the-crossing.html",
            "url": "https://frau-urlaub-on-tour.github.io/norway-2023/the-crossing.html",
            "title": "Denmark",
            "summary": "After a short night with barely 5 hours of sleep&hellip;",
            "content_html": "<p>After a short night with barely 5 hours of sleep (is it apprehension that prevents me from drifting off?), it's \"get up and get going\" onto the second leg of my journey. The 630 km to the North of Denmark are pretty boring driving through mostly very flat countryside. Despite losing about an hour near Hamburg in a traffic jam, I am at my destination 3 hours early. Which means more boredom waiting for the Fjordline check-in counters to open.</p>\n<div class=\"gallery-wrapper\"><div class=\"gallery\"  data-is-empty=\"false\" data-translation=\"Add images\" data-columns=\"3\">\n<figure class=\"gallery__item\"><a href=\"https://frau-urlaub-on-tour.github.io/norway-2023/media/posts/29/gallery/DSC05767.JPG\" data-size=\"1920x1080\"><img loading=\"lazy\" src=\"https://frau-urlaub-on-tour.github.io/norway-2023/media/posts/29/gallery/DSC05767-thumbnail.JPG\" alt=\"\" width=\"720\" height=\"405\"></a></figure>\n<figure class=\"gallery__item\"><a href=\"https://frau-urlaub-on-tour.github.io/norway-2023/media/posts/29/gallery/DSC05768.JPG\" data-size=\"1923x1080\"><img loading=\"lazy\" src=\"https://frau-urlaub-on-tour.github.io/norway-2023/media/posts/29/gallery/DSC05768-thumbnail.JPG\" alt=\"\" width=\"720\" height=\"404\"></a></figure>\n<figure class=\"gallery__item\"><a href=\"https://frau-urlaub-on-tour.github.io/norway-2023/media/posts/29/gallery/IMG_20230821_192851412.jpg\" data-size=\"3264x1836\"><img loading=\"lazy\" src=\"https://frau-urlaub-on-tour.github.io/norway-2023/media/posts/29/gallery/IMG_20230821_192851412-thumbnail.jpg\" alt=\"\" width=\"720\" height=\"405\"></a></figure>\n</div></div>\n<p class=\"align-center\">Click on the gallery then swipe or use ← → keys</p>",
            "image": "https://frau-urlaub-on-tour.github.io/norway-2023/media/posts/29/DSC05766.JPG",
            "author": {
                "name": "Petra"
            },
            "tags": [
            ],
            "date_published": "2023-08-21T18:13:00+02:00",
            "date_modified": "2023-08-22T22:02:05+02:00"
        },
        {
            "id": "https://frau-urlaub-on-tour.github.io/norway-2023/bremen.html",
            "url": "https://frau-urlaub-on-tour.github.io/norway-2023/bremen.html",
            "title": "Stopover in Bremen",
            "summary": "After the first stretch of almost 580 km, it's time&hellip;",
            "content_html": "<p>After the first stretch of almost 580 km, it's time for a weekend stopover in the town I grew up in. Sunday is warm and sunny; time to take out the bike for a ride. </p>\n<div class=\"gallery-wrapper\"><div class=\"gallery\"  data-is-empty=\"false\" data-translation=\"Add images\" data-columns=\"3\">\n<figure class=\"gallery__item\"><a href=\"https://frau-urlaub-on-tour.github.io/norway-2023/media/posts/28/gallery/IMG_0974.JPG\" data-size=\"1920x1080\"><img loading=\"lazy\" src=\"https://frau-urlaub-on-tour.github.io/norway-2023/media/posts/28/gallery/IMG_0974-thumbnail.JPG\" alt=\"\" width=\"720\" height=\"405\"></a></figure>\n<figure class=\"gallery__item\"><a href=\"https://frau-urlaub-on-tour.github.io/norway-2023/media/posts/28/gallery/IMG_0977.JPG\" data-size=\"1920x1080\"><img loading=\"lazy\" src=\"https://frau-urlaub-on-tour.github.io/norway-2023/media/posts/28/gallery/IMG_0977-thumbnail.JPG\" alt=\"\" width=\"720\" height=\"405\"></a></figure>\n<figure class=\"gallery__item\"><a href=\"https://frau-urlaub-on-tour.github.io/norway-2023/media/posts/28/gallery/IMG_0979.JPG\" data-size=\"1920x1080\"><img loading=\"lazy\" src=\"https://frau-urlaub-on-tour.github.io/norway-2023/media/posts/28/gallery/IMG_0979-thumbnail.JPG\" alt=\"\" width=\"720\" height=\"405\"></a></figure>\n<figure class=\"gallery__item\"><a href=\"https://frau-urlaub-on-tour.github.io/norway-2023/media/posts/28/gallery/DSC05724.JPG\" data-size=\"1921x1080\"><img loading=\"lazy\" src=\"https://frau-urlaub-on-tour.github.io/norway-2023/media/posts/28/gallery/DSC05724-thumbnail.JPG\" alt=\"\" width=\"720\" height=\"405\"></a></figure>\n<figure class=\"gallery__item\"><a href=\"https://frau-urlaub-on-tour.github.io/norway-2023/media/posts/28/gallery/DSC05725.JPG\" data-size=\"1921x1080\"><img loading=\"lazy\" src=\"https://frau-urlaub-on-tour.github.io/norway-2023/media/posts/28/gallery/DSC05725-thumbnail.JPG\" alt=\"\" width=\"720\" height=\"405\"></a></figure>\n<figure class=\"gallery__item\"><a href=\"https://frau-urlaub-on-tour.github.io/norway-2023/media/posts/28/gallery/DSC05726.JPG\" data-size=\"1921x1080\"><img loading=\"lazy\" src=\"https://frau-urlaub-on-tour.github.io/norway-2023/media/posts/28/gallery/DSC05726-thumbnail.JPG\" alt=\"\" width=\"720\" height=\"405\"></a></figure>\n<figure class=\"gallery__item\"><a href=\"https://frau-urlaub-on-tour.github.io/norway-2023/media/posts/28/gallery/DSC05729.JPG\" data-size=\"1921x1080\"><img loading=\"lazy\" src=\"https://frau-urlaub-on-tour.github.io/norway-2023/media/posts/28/gallery/DSC05729-thumbnail.JPG\" alt=\"\" width=\"720\" height=\"405\"></a></figure>\n<figure class=\"gallery__item\"><a href=\"https://frau-urlaub-on-tour.github.io/norway-2023/media/posts/28/gallery/DSC05730.JPG\" data-size=\"1923x1080\"><img loading=\"lazy\" src=\"https://frau-urlaub-on-tour.github.io/norway-2023/media/posts/28/gallery/DSC05730-thumbnail.JPG\" alt=\"\" width=\"720\" height=\"404\"></a></figure>\n<figure class=\"gallery__item\"><a href=\"https://frau-urlaub-on-tour.github.io/norway-2023/media/posts/28/gallery/DSC05731.JPG\" data-size=\"1920x1080\"><img loading=\"lazy\" src=\"https://frau-urlaub-on-tour.github.io/norway-2023/media/posts/28/gallery/DSC05731-thumbnail.JPG\" alt=\"\" width=\"720\" height=\"405\"></a></figure>\n<figure class=\"gallery__item\"><a href=\"https://frau-urlaub-on-tour.github.io/norway-2023/media/posts/28/gallery/DSC05736.JPG\" data-size=\"1921x1080\"><img loading=\"lazy\" src=\"https://frau-urlaub-on-tour.github.io/norway-2023/media/posts/28/gallery/DSC05736-thumbnail.JPG\" alt=\"\" width=\"720\" height=\"405\"></a></figure>\n<figure class=\"gallery__item\"><a href=\"https://frau-urlaub-on-tour.github.io/norway-2023/media/posts/28/gallery/IMG_20211004_100827.jpg\" data-size=\"1920x1080\"><img loading=\"lazy\" src=\"https://frau-urlaub-on-tour.github.io/norway-2023/media/posts/28/gallery/IMG_20211004_100827-thumbnail.jpg\" alt=\"\" width=\"720\" height=\"405\"></a></figure>\n<figure class=\"gallery__item\"><a href=\"https://frau-urlaub-on-tour.github.io/norway-2023/media/posts/28/gallery/DSC05737.JPG\" data-size=\"1923x1080\"><img loading=\"lazy\" src=\"https://frau-urlaub-on-tour.github.io/norway-2023/media/posts/28/gallery/DSC05737-thumbnail.JPG\" alt=\"\" width=\"720\" height=\"404\"></a></figure>\n<figure class=\"gallery__item\"><a href=\"https://frau-urlaub-on-tour.github.io/norway-2023/media/posts/28/gallery/DSC05738.JPG\" data-size=\"1923x1080\"><img loading=\"lazy\" src=\"https://frau-urlaub-on-tour.github.io/norway-2023/media/posts/28/gallery/DSC05738-thumbnail.JPG\" alt=\"\" width=\"720\" height=\"404\"></a></figure>\n<figure class=\"gallery__item\"><a href=\"https://frau-urlaub-on-tour.github.io/norway-2023/media/posts/28/gallery/DSC05739.JPG\" data-size=\"1923x1080\"><img loading=\"lazy\" src=\"https://frau-urlaub-on-tour.github.io/norway-2023/media/posts/28/gallery/DSC05739-thumbnail.JPG\" alt=\"\" width=\"720\" height=\"404\"></a></figure>\n<figure class=\"gallery__item\"><a href=\"https://frau-urlaub-on-tour.github.io/norway-2023/media/posts/28/gallery/DSC05744.JPG\" data-size=\"1923x1021\"><img loading=\"lazy\" src=\"https://frau-urlaub-on-tour.github.io/norway-2023/media/posts/28/gallery/DSC05744-thumbnail.JPG\" alt=\"\" width=\"720\" height=\"382\"></a></figure>\n<figure class=\"gallery__item\"><a href=\"https://frau-urlaub-on-tour.github.io/norway-2023/media/posts/28/gallery/DSC05747.JPG\" data-size=\"1921x1080\"><img loading=\"lazy\" src=\"https://frau-urlaub-on-tour.github.io/norway-2023/media/posts/28/gallery/DSC05747-thumbnail.JPG\" alt=\"\" width=\"720\" height=\"405\"></a></figure>\n<figure class=\"gallery__item\"><a href=\"https://frau-urlaub-on-tour.github.io/norway-2023/media/posts/28/gallery/DSC05748.JPG\" data-size=\"1920x1080\"><img loading=\"lazy\" src=\"https://frau-urlaub-on-tour.github.io/norway-2023/media/posts/28/gallery/DSC05748-thumbnail.JPG\" alt=\"\" width=\"720\" height=\"405\"></a></figure>\n<figure class=\"gallery__item\"><a href=\"https://frau-urlaub-on-tour.github.io/norway-2023/media/posts/28/gallery/DSC05750.JPG\" data-size=\"1923x1080\"><img loading=\"lazy\" src=\"https://frau-urlaub-on-tour.github.io/norway-2023/media/posts/28/gallery/DSC05750-thumbnail.JPG\" alt=\"\" width=\"720\" height=\"404\"></a></figure>\n<figure class=\"gallery__item\"><a href=\"https://frau-urlaub-on-tour.github.io/norway-2023/media/posts/28/gallery/DSC05751.JPG\" data-size=\"1923x1030\"><img loading=\"lazy\" src=\"https://frau-urlaub-on-tour.github.io/norway-2023/media/posts/28/gallery/DSC05751-thumbnail.JPG\" alt=\"\" width=\"720\" height=\"386\"></a></figure>\n<figure class=\"gallery__item\"><a href=\"https://frau-urlaub-on-tour.github.io/norway-2023/media/posts/28/gallery/DSC05753.JPG\" data-size=\"1920x1080\"><img loading=\"lazy\" src=\"https://frau-urlaub-on-tour.github.io/norway-2023/media/posts/28/gallery/DSC05753-thumbnail.JPG\" alt=\"\" width=\"720\" height=\"405\"></a></figure>\n<figure class=\"gallery__item\"><a href=\"https://frau-urlaub-on-tour.github.io/norway-2023/media/posts/28/gallery/DSC05757.JPG\" data-size=\"1920x1080\"><img loading=\"lazy\" src=\"https://frau-urlaub-on-tour.github.io/norway-2023/media/posts/28/gallery/DSC05757-thumbnail.JPG\" alt=\"\" width=\"720\" height=\"405\"></a></figure>\n<figure class=\"gallery__item\"><a href=\"https://frau-urlaub-on-tour.github.io/norway-2023/media/posts/28/gallery/DSC05760.JPG\" data-size=\"1923x1080\"><img loading=\"lazy\" src=\"https://frau-urlaub-on-tour.github.io/norway-2023/media/posts/28/gallery/DSC05760-thumbnail.JPG\" alt=\"\" width=\"720\" height=\"404\"></a></figure>\n<figure class=\"gallery__item\"><a href=\"https://frau-urlaub-on-tour.github.io/norway-2023/media/posts/28/gallery/DSC05761.JPG\" data-size=\"1923x1080\"><img loading=\"lazy\" src=\"https://frau-urlaub-on-tour.github.io/norway-2023/media/posts/28/gallery/DSC05761-thumbnail.JPG\" alt=\"\" width=\"720\" height=\"404\"></a></figure>\n<figure class=\"gallery__item\"><a href=\"https://frau-urlaub-on-tour.github.io/norway-2023/media/posts/28/gallery/DSC05764.JPG\" data-size=\"1923x1080\"><img loading=\"lazy\" src=\"https://frau-urlaub-on-tour.github.io/norway-2023/media/posts/28/gallery/DSC05764-thumbnail.JPG\" alt=\"\" width=\"720\" height=\"404\"></a></figure>\n</div></div>\n<p class=\"align-center\">Click on the gallery then swipe or use ← → keys</p>",
            "image": "https://frau-urlaub-on-tour.github.io/norway-2023/media/posts/28/IMG_0961.JPG",
            "author": {
                "name": "Petra"
            },
            "tags": [
            ],
            "date_published": "2023-08-20T19:34:00+02:00",
            "date_modified": "2023-08-22T22:01:58+02:00"
        },
        {
            "id": "https://frau-urlaub-on-tour.github.io/norway-2023/post1.html",
            "url": "https://frau-urlaub-on-tour.github.io/norway-2023/post1.html",
            "title": "The Route",
            "summary": "It'll be a lot of driving from the South West&hellip;",
            "content_html": "<p>It'll be a lot of driving from the South West of Germany up to the very North of Norway. The first stretch will take me in 580 km from Neustadt to Bremen. After a two-day break and another drive of 630 km I will reach the ferry port of Hirtshals in Denmark. From there it'll be a 16,5 hour night crossing on the car ferry to Bergen. </p>\n<p>The next 4 days will be spent going further up the West coast of Norway, 1.480 km in total, to reach Bodo on Friday, 25 August. Here, I will pick up Medha at the airport. Together, we will cross over to the Lofoten which we intend to explore during the following week. Hopefully not only in the rain; we'll see. The weather is known to be very unpredictable up there.</p>\n<div class=\"gallery-wrapper\"><div class=\"gallery\"  data-is-empty=\"false\" data-translation=\"Add images\" data-columns=\"3\">\n<figure class=\"gallery__item\"><a href=\"https://frau-urlaub-on-tour.github.io/norway-2023/media/posts/27/gallery/Hirtshals-to-Bergen-2.jpg\" data-size=\"1273x664\"><img loading=\"lazy\" src=\"https://frau-urlaub-on-tour.github.io/norway-2023/media/posts/27/gallery/Hirtshals-to-Bergen-2-thumbnail.jpg\" alt=\"\" width=\"720\" height=\"376\"></a></figure>\n<figure class=\"gallery__item\"><a href=\"https://frau-urlaub-on-tour.github.io/norway-2023/media/posts/27/gallery/Bergen-to-Bodo-2.jpg\" data-size=\"1222x737\"><img loading=\"lazy\" src=\"https://frau-urlaub-on-tour.github.io/norway-2023/media/posts/27/gallery/Bergen-to-Bodo-2-thumbnail.jpg\" alt=\"\" width=\"720\" height=\"434\"></a></figure>\n<figure class=\"gallery__item\"><a href=\"https://frau-urlaub-on-tour.github.io/norway-2023/media/posts/27/gallery/Bodo-to-Moskenes-2.jpg\" data-size=\"1263x724\"><img loading=\"lazy\" src=\"https://frau-urlaub-on-tour.github.io/norway-2023/media/posts/27/gallery/Bodo-to-Moskenes-2-thumbnail.jpg\" alt=\"\" width=\"720\" height=\"413\"></a></figure>\n</div></div>\n<p class=\"align-center\">Click on the gallery then swipe or use ← → keys</p>",
            "image": "https://frau-urlaub-on-tour.github.io/norway-2023/media/posts/27/Neustadt-to-Denmark.jpg",
            "author": {
                "name": "Petra"
            },
            "tags": [
            ],
            "date_published": "2023-08-13T10:55:00+02:00",
            "date_modified": "2023-08-22T22:01:48+02:00"
        }
    ]
}
